{
  "111": {
    "name": "lavender",
    "id": "111",
    "nation": "han",
    "klass": "131",
    "score": [
      {
        "math": 89
      },
      {
        "english": 90
      }
    ]
  },
  "112": {
    "name": "lavender",
    "id": "112",
    "nation": "han",
    "klass": "131",
    "score": [
      {
        "math": 89
      },
      {
        "english": 90
      }
    ]
  },
  "113": {
    "name": "AAA",
    "id": "113",
    "nation": "han",
    "klass": "131",
    "score": [
      {
        "math": 89
      },
      {
        "english": 90
      }
    ]
  }
}
